itsalive/__init__.py
itsalive/cli.py
itsalive/presenter_view.py
itsalive/version.py
itsalive-0.2.4.dist-info/entry_points.txt
itsalive-0.2.4.dist-info/LICENSE
itsalive-0.2.4.dist-info/WHEEL
itsalive-0.2.4.dist-info/METADATA
itsalive-0.2.4.dist-info/RECORD
