Metadata-Version: 2.1
Name: itsalive
Version: 0.2.4
Summary: Autopilot for live demos.
Home-page: https://gitlab.com/stavros/itsalive
License: GPL-3.0-or-later
Author: Stavros Korokithakis
Author-email: hi@stavros.io
Requires-Python: >=3.5,<4.0
Classifier: License :: OSI Approved :: GNU General Public License v3 or later (GPLv3+)
Classifier: Programming Language :: Python :: 3
Classifier: Programming Language :: Python :: 3.10
Classifier: Programming Language :: Python :: 3.5
Classifier: Programming Language :: Python :: 3.6
Classifier: Programming Language :: Python :: 3.7
Classifier: Programming Language :: Python :: 3.8
Classifier: Programming Language :: Python :: 3.9
Project-URL: Repository, https://gitlab.com/stavros/itsalive
